tantivy-0.25.0.dist-info/METADATA
tantivy-0.25.0.dist-info/WHEEL
tantivy-0.25.0.dist-info/license_files/LICENSE
tantivy/tantivy.pyi
tantivy/__init__.py
tantivy/py.typed
tantivy/tantivy.cpython-313-x86_64-linux-gnu.so
tantivy-0.25.0.dist-info/RECORD
