Metadata-Version: 2.1
Name: tantivy
Version: 0.25.0
Requires-Dist: nox ; extra == 'dev'
Provides-Extra: dev
License-File: LICENSE
Summary: Official Python bindings for the Tantivy search engine
Author: Damir Jelić <poljar@termina.org.uk>
Author-email: Damir Jelić <poljar@termina.org.uk>, Caleb Hattingh <code@cjrh.info>, Cam Parry <cam.parry@kapiche.com>
License: MIT
Requires-Python: >=3.9
